scoreunlocked/__init__.py
scoreunlocked/scoreunlocked_client.py
scoreunlocked-0.0.2.dist-info/LICENSE
scoreunlocked-0.0.2.dist-info/METADATA
scoreunlocked-0.0.2.dist-info/WHEEL
scoreunlocked-0.0.2.dist-info/top_level.txt
scoreunlocked-0.0.2.dist-info/RECORD
