Metadata-Version: 2.1
Name: scoreunlocked
Version: 0.0.2
Summary: A simple package for using the ScoreUnlocked leaderboard system running at scoreunlocked.pythonanywhere.com
Author-email: Tank King <tankking9833@gmail.com>
License: MIT License        
Project-URL: Homepage, https://github.com/tank-king/scoreunlocked
Project-URL: Bug Tracker, https://github.com/tank-king/scoreunlocked/issues
Classifier: Programming Language :: Python :: 3
Classifier: License :: OSI Approved :: MIT License
Classifier: Operating System :: OS Independent
Requires-Python: >=3.7
License-File: LICENSE
